[{"timestamp":"2024-02-01T00:34:49.765Z","count":0,"uniques":0},{"timestamp":"2024-02-02T00:33:21.264Z","count":0,"uniques":0},{"timestamp":"2024-02-03T00:32:57.622Z","count":0,"uniques":0},{"timestamp":"2024-02-04T00:36:08.244Z","count":0,"uniques":0},{"timestamp":"2024-02-05T00:34:21.916Z","count":0,"uniques":0},{"timestamp":"2024-02-06T00:00:00.000Z","count":1,"uniques":1},{"timestamp":"2024-02-07T00:31:19.954Z","count":0,"uniques":0},{"timestamp":"2024-02-08T00:32:41.479Z","count":0,"uniques":0},{"timestamp":"2024-02-09T00:32:13.276Z","count":0,"uniques":0},{"timestamp":"2024-02-10T00:31:44.822Z","count":0,"uniques":0},{"timestamp":"2024-02-11T00:35:58.617Z","count":0,"uniques":0},{"timestamp":"2024-02-12T00:33:41.541Z","count":0,"uniques":0},{"timestamp":"2024-02-13T00:33:38.314Z","count":0,"uniques":0},{"timestamp":"2024-02-14T00:32:59.079Z","count":0,"uniques":0},{"timestamp":"2024-02-15T00:32:44.002Z","count":0,"uniques":0},{"timestamp":"2024-02-16T00:32:19.434Z","count":0,"uniques":0},{"timestamp":"2024-02-17T00:32:23.163Z","count":0,"uniques":0},{"timestamp":"2024-02-18T00:35:23.521Z","count":0,"uniques":0},{"timestamp":"2024-02-19T00:34:10.361Z","count":0,"uniques":0},{"timestamp":"2024-02-20T00:32:29.745Z","count":0,"uniques":0},{"timestamp":"2024-02-21T00:32:45.240Z","count":0,"uniques":0},{"timestamp":"2024-02-22T00:32:46.858Z","count":0,"uniques":0},{"timestamp":"2024-02-23T00:32:35.368Z","count":0,"uniques":0},{"timestamp":"2024-02-24T00:30:57.989Z","count":0,"uniques":0},{"timestamp":"2024-02-25T00:36:01.212Z","count":0,"uniques":0},{"timestamp":"2024-02-26T00:34:25.131Z","count":0,"uniques":0},{"timestamp":"2024-02-27T00:32:34.373Z","count":0,"uniques":0},{"timestamp":"2024-02-28T00:31:52.345Z","count":0,"uniques":0},{"timestamp":"2024-02-29T00:00:00.000Z","count":4,"uniques":1},{"timestamp":"2024-03-01T00:36:55.137Z","count":0,"uniques":0},{"timestamp":"2024-03-02T00:31:56.627Z","count":0,"uniques":0}]
