[{"timestamp":"2025-02-28T00:46:06.756Z","count":0,"uniques":0},{"timestamp":"2025-03-01T00:51:24.882Z","count":0,"uniques":0},{"timestamp":"2025-03-02T00:50:13.895Z","count":0,"uniques":0},{"timestamp":"2025-03-03T00:48:40.589Z","count":0,"uniques":0},{"timestamp":"2025-03-04T00:47:06.520Z","count":0,"uniques":0},{"timestamp":"2025-03-05T00:46:58.828Z","count":0,"uniques":0},{"timestamp":"2025-03-06T00:46:52.662Z","count":0,"uniques":0},{"timestamp":"2025-03-07T00:47:23.209Z","count":0,"uniques":0}]
