[{"timestamp":"2025-01-19T00:47:42.695Z","count":0,"uniques":0},{"timestamp":"2025-01-20T00:44:35.513Z","count":0,"uniques":0},{"timestamp":"2025-01-21T00:43:19.430Z","count":0,"uniques":0},{"timestamp":"2025-01-22T00:44:37.767Z","count":0,"uniques":0},{"timestamp":"2025-01-23T00:43:51.441Z","count":0,"uniques":0},{"timestamp":"2025-01-24T00:43:41.279Z","count":0,"uniques":0},{"timestamp":"2025-01-25T00:42:23.637Z","count":0,"uniques":0},{"timestamp":"2025-01-26T00:44:59.460Z","count":0,"uniques":0}]
