[{"timestamp":"2024-06-29T00:41:16.471Z","count":0,"uniques":0},{"timestamp":"2024-06-30T00:45:43.859Z","count":0,"uniques":0},{"timestamp":"2024-07-01T00:48:01.717Z","count":0,"uniques":0},{"timestamp":"2024-07-02T00:42:09.084Z","count":0,"uniques":0},{"timestamp":"2024-07-03T00:42:04.337Z","count":0,"uniques":0},{"timestamp":"2024-07-04T00:42:19.372Z","count":0,"uniques":0},{"timestamp":"2024-07-05T06:17:19.175Z","count":0,"uniques":0},{"timestamp":"2024-07-06T00:40:57.381Z","count":0,"uniques":0}]
