[{"timestamp":"2024-01-29T00:35:46.084Z","count":0,"uniques":0},{"timestamp":"2024-01-30T00:35:58.561Z","count":0,"uniques":0},{"timestamp":"2024-01-31T00:35:45.392Z","count":0,"uniques":0},{"timestamp":"2024-02-01T00:37:36.275Z","count":0,"uniques":0},{"timestamp":"2024-02-02T00:35:53.019Z","count":0,"uniques":0},{"timestamp":"2024-02-03T00:35:35.664Z","count":0,"uniques":0},{"timestamp":"2024-02-04T00:38:58.982Z","count":0,"uniques":0},{"timestamp":"2024-02-05T00:36:50.965Z","count":0,"uniques":0}]
