[{"timestamp":"2024-07-13T00:46:25.913Z","count":0,"uniques":0},{"timestamp":"2024-07-14T00:49:52.656Z","count":0,"uniques":0},{"timestamp":"2024-07-15T00:48:07.421Z","count":0,"uniques":0},{"timestamp":"2024-07-16T00:46:02.493Z","count":0,"uniques":0},{"timestamp":"2024-07-17T00:46:40.578Z","count":0,"uniques":0},{"timestamp":"2024-07-18T00:46:11.534Z","count":0,"uniques":0},{"timestamp":"2024-07-19T00:46:03.957Z","count":0,"uniques":0},{"timestamp":"2024-07-20T00:45:07.323Z","count":0,"uniques":0},{"timestamp":"2024-07-21T00:50:49.192Z","count":0,"uniques":0},{"timestamp":"2024-07-22T00:47:39.747Z","count":0,"uniques":0},{"timestamp":"2024-07-23T00:46:19.018Z","count":0,"uniques":0},{"timestamp":"2024-07-24T00:47:13.619Z","count":0,"uniques":0},{"timestamp":"2024-07-25T00:46:27.846Z","count":0,"uniques":0},{"timestamp":"2024-07-26T00:45:47.028Z","count":0,"uniques":0},{"timestamp":"2024-07-27T00:46:45.816Z","count":0,"uniques":0},{"timestamp":"2024-07-28T00:51:09.137Z","count":0,"uniques":0},{"timestamp":"2024-07-29T00:47:45.723Z","count":0,"uniques":0},{"timestamp":"2024-07-30T00:47:23.651Z","count":0,"uniques":0},{"timestamp":"2024-07-31T00:39:18.496Z","count":0,"uniques":0},{"timestamp":"2024-08-01T00:50:17.691Z","count":0,"uniques":0},{"timestamp":"2024-08-02T00:45:58.675Z","count":0,"uniques":0},{"timestamp":"2024-08-03T00:45:38.563Z","count":0,"uniques":0},{"timestamp":"2024-08-04T00:50:58.142Z","count":0,"uniques":0},{"timestamp":"2024-08-05T00:49:26.544Z","count":0,"uniques":0},{"timestamp":"2024-08-06T00:46:48.760Z","count":0,"uniques":0},{"timestamp":"2024-08-07T00:47:05.064Z","count":0,"uniques":0},{"timestamp":"2024-08-08T00:46:54.986Z","count":0,"uniques":0},{"timestamp":"2024-08-09T00:47:50.315Z","count":0,"uniques":0},{"timestamp":"2024-08-10T00:46:50.056Z","count":0,"uniques":0},{"timestamp":"2024-08-11T00:51:27.115Z","count":0,"uniques":0},{"timestamp":"2024-08-12T00:48:26.196Z","count":0,"uniques":0}]
