[{"timestamp":"2023-12-31T00:42:54.558Z","count":0,"uniques":0},{"timestamp":"2024-01-01T00:45:02.063Z","count":0,"uniques":0},{"timestamp":"2024-01-02T00:40:11.793Z","count":0,"uniques":0},{"timestamp":"2024-01-03T00:40:37.507Z","count":0,"uniques":0},{"timestamp":"2024-01-04T00:41:40.063Z","count":0,"uniques":0},{"timestamp":"2024-01-05T00:41:22.839Z","count":0,"uniques":0},{"timestamp":"2024-01-06T00:41:16.628Z","count":0,"uniques":0},{"timestamp":"2024-01-07T00:44:48.506Z","count":0,"uniques":0},{"timestamp":"2024-01-08T00:42:34.237Z","count":0,"uniques":0},{"timestamp":"2024-01-09T00:42:17.289Z","count":0,"uniques":0},{"timestamp":"2024-01-10T00:41:43.125Z","count":0,"uniques":0},{"timestamp":"2024-01-11T00:41:29.098Z","count":0,"uniques":0},{"timestamp":"2024-01-12T00:42:07.286Z","count":0,"uniques":0},{"timestamp":"2024-01-13T00:41:47.761Z","count":0,"uniques":0},{"timestamp":"2024-01-14T00:44:27.025Z","count":0,"uniques":0},{"timestamp":"2024-01-15T00:43:02.881Z","count":0,"uniques":0},{"timestamp":"2024-01-16T00:41:21.217Z","count":0,"uniques":0},{"timestamp":"2024-01-17T00:41:33.511Z","count":0,"uniques":0},{"timestamp":"2024-01-18T00:41:12.141Z","count":0,"uniques":0},{"timestamp":"2024-01-19T00:41:43.200Z","count":0,"uniques":0},{"timestamp":"2024-01-20T00:41:04.716Z","count":0,"uniques":0},{"timestamp":"2024-01-21T00:44:53.534Z","count":0,"uniques":0},{"timestamp":"2024-01-22T00:43:35.535Z","count":0,"uniques":0},{"timestamp":"2024-01-23T00:42:10.054Z","count":0,"uniques":0},{"timestamp":"2024-01-24T00:42:17.826Z","count":0,"uniques":0},{"timestamp":"2024-01-25T00:42:52.838Z","count":0,"uniques":0},{"timestamp":"2024-01-26T00:40:13.083Z","count":0,"uniques":0},{"timestamp":"2024-01-27T00:39:40.292Z","count":0,"uniques":0},{"timestamp":"2024-01-28T00:42:18.785Z","count":0,"uniques":0},{"timestamp":"2024-01-29T00:39:15.741Z","count":0,"uniques":0},{"timestamp":"2024-01-30T00:39:59.649Z","count":0,"uniques":0}]
