[{"timestamp":"2025-02-02T00:53:21.804Z","count":0,"uniques":0},{"timestamp":"2025-02-03T00:51:48.074Z","count":0,"uniques":0},{"timestamp":"2025-02-04T00:51:29.807Z","count":0,"uniques":0},{"timestamp":"2025-02-05T00:51:37.758Z","count":0,"uniques":0},{"timestamp":"2025-02-06T00:50:57.712Z","count":0,"uniques":0},{"timestamp":"2025-02-07T00:50:57.343Z","count":0,"uniques":0},{"timestamp":"2025-02-08T00:49:54.700Z","count":0,"uniques":0},{"timestamp":"2025-02-09T00:54:19.493Z","count":0,"uniques":0}]
