[{"timestamp":"2024-10-31T00:51:31.054Z","count":0,"uniques":0},{"timestamp":"2024-11-01T00:56:39.844Z","count":0,"uniques":0},{"timestamp":"2024-11-02T00:50:15.797Z","count":0,"uniques":0},{"timestamp":"2024-11-03T00:55:29.753Z","count":0,"uniques":0},{"timestamp":"2024-11-04T00:52:52.787Z","count":0,"uniques":0},{"timestamp":"2024-11-05T00:50:19.832Z","count":0,"uniques":0},{"timestamp":"2024-11-06T00:50:25.715Z","count":0,"uniques":0},{"timestamp":"2024-11-07T00:50:07.858Z","count":0,"uniques":0}]
