[{"timestamp":"2023-11-02T00:38:10.404Z","count":0,"uniques":0},{"timestamp":"2023-11-03T00:39:15.838Z","count":0,"uniques":0},{"timestamp":"2023-11-04T00:39:37.147Z","count":0,"uniques":0},{"timestamp":"2023-11-05T00:39:56.389Z","count":0,"uniques":0},{"timestamp":"2023-11-06T00:43:02.770Z","count":0,"uniques":0},{"timestamp":"2023-11-07T00:39:15.176Z","count":0,"uniques":0},{"timestamp":"2023-11-08T00:37:33.774Z","count":0,"uniques":0},{"timestamp":"2023-11-09T00:39:15.066Z","count":0,"uniques":0},{"timestamp":"2023-11-10T00:38:43.137Z","count":0,"uniques":0},{"timestamp":"2023-11-11T00:36:44.632Z","count":0,"uniques":0},{"timestamp":"2023-11-12T00:40:32.176Z","count":0,"uniques":0},{"timestamp":"2023-11-13T00:40:38.774Z","count":0,"uniques":0},{"timestamp":"2023-11-14T00:39:43.297Z","count":0,"uniques":0},{"timestamp":"2023-11-15T00:38:24.340Z","count":0,"uniques":0},{"timestamp":"2023-11-16T00:39:10.056Z","count":0,"uniques":0},{"timestamp":"2023-11-17T00:38:52.175Z","count":0,"uniques":0},{"timestamp":"2023-11-18T00:38:28.736Z","count":0,"uniques":0},{"timestamp":"2023-11-19T00:41:41.952Z","count":0,"uniques":0},{"timestamp":"2023-11-20T00:39:49.326Z","count":0,"uniques":0},{"timestamp":"2023-11-21T00:40:25.146Z","count":0,"uniques":0},{"timestamp":"2023-11-22T00:41:04.268Z","count":0,"uniques":0},{"timestamp":"2023-11-23T00:38:58.348Z","count":0,"uniques":0},{"timestamp":"2023-11-24T00:38:11.109Z","count":0,"uniques":0},{"timestamp":"2023-11-25T00:37:34.603Z","count":0,"uniques":0},{"timestamp":"2023-11-26T00:42:12.154Z","count":0,"uniques":0},{"timestamp":"2023-11-27T00:39:49.275Z","count":0,"uniques":0},{"timestamp":"2023-11-28T00:39:58.789Z","count":0,"uniques":0},{"timestamp":"2023-11-29T00:39:47.841Z","count":0,"uniques":0},{"timestamp":"2023-11-30T00:39:46.877Z","count":0,"uniques":0},{"timestamp":"2023-12-01T00:00:00.000Z","count":1,"uniques":1},{"timestamp":"2023-12-02T00:38:30.616Z","count":0,"uniques":0}]
