[{"timestamp":"2025-02-22T00:47:43.759Z","count":0,"uniques":0},{"timestamp":"2025-02-23T00:54:03.491Z","count":0,"uniques":0},{"timestamp":"2025-02-24T00:51:27.148Z","count":0,"uniques":0},{"timestamp":"2025-02-25T00:50:52.511Z","count":0,"uniques":0},{"timestamp":"2025-02-26T00:50:06.877Z","count":0,"uniques":0},{"timestamp":"2025-02-27T00:50:40.191Z","count":0,"uniques":0},{"timestamp":"2025-02-28T00:50:19.043Z","count":0,"uniques":0},{"timestamp":"2025-03-01T00:55:59.792Z","count":0,"uniques":0}]
