[{"timestamp":"2025-03-04T00:50:11.377Z","count":0,"uniques":0},{"timestamp":"2025-03-05T00:50:04.401Z","count":0,"uniques":0},{"timestamp":"2025-03-06T00:49:57.136Z","count":0,"uniques":0},{"timestamp":"2025-03-07T00:50:36.471Z","count":0,"uniques":0},{"timestamp":"2025-03-08T00:40:26.430Z","count":0,"uniques":0},{"timestamp":"2025-03-09T00:44:33.589Z","count":0,"uniques":0},{"timestamp":"2025-03-10T00:42:55.776Z","count":0,"uniques":0},{"timestamp":"2025-03-11T00:50:52.809Z","count":0,"uniques":0}]
