[{"timestamp":"2024-12-18T00:50:09.182Z","count":0,"uniques":0},{"timestamp":"2024-12-19T00:50:51.590Z","count":0,"uniques":0},{"timestamp":"2024-12-20T00:48:14.814Z","count":0,"uniques":0},{"timestamp":"2024-12-21T00:47:21.871Z","count":0,"uniques":0},{"timestamp":"2024-12-22T00:53:21.978Z","count":0,"uniques":0},{"timestamp":"2024-12-23T00:49:20.566Z","count":0,"uniques":0},{"timestamp":"2024-12-24T00:47:42.652Z","count":0,"uniques":0},{"timestamp":"2024-12-25T00:47:07.429Z","count":0,"uniques":0}]
