[{"timestamp":"2024-09-15T00:48:34.944Z","count":0,"uniques":0},{"timestamp":"2024-09-16T00:45:45.607Z","count":0,"uniques":0},{"timestamp":"2024-09-17T00:36:08.887Z","count":0,"uniques":0},{"timestamp":"2024-09-18T00:43:00.301Z","count":0,"uniques":0},{"timestamp":"2024-09-19T00:43:37.627Z","count":0,"uniques":0},{"timestamp":"2024-09-20T00:43:30.225Z","count":0,"uniques":0},{"timestamp":"2024-09-21T00:42:47.116Z","count":0,"uniques":0},{"timestamp":"2024-09-22T00:48:45.766Z","count":0,"uniques":0}]
