[{"timestamp":"2024-09-28T00:47:12.146Z","count":0,"uniques":0},{"timestamp":"2024-09-29T00:52:31.839Z","count":0,"uniques":0},{"timestamp":"2024-09-30T00:49:27.686Z","count":0,"uniques":0},{"timestamp":"2024-10-01T00:53:22.578Z","count":0,"uniques":0},{"timestamp":"2024-10-02T00:48:09.225Z","count":0,"uniques":0},{"timestamp":"2024-10-03T00:47:58.942Z","count":0,"uniques":0},{"timestamp":"2024-10-04T00:47:46.632Z","count":0,"uniques":0},{"timestamp":"2024-10-05T00:47:37.136Z","count":0,"uniques":0}]
