[{"timestamp":"2024-04-27T00:35:35.195Z","count":0,"uniques":0},{"timestamp":"2024-04-28T00:39:24.085Z","count":0,"uniques":0},{"timestamp":"2024-04-29T00:36:34.037Z","count":0,"uniques":0},{"timestamp":"2024-04-30T00:34:50.433Z","count":0,"uniques":0},{"timestamp":"2024-05-01T00:38:34.776Z","count":0,"uniques":0},{"timestamp":"2024-05-02T00:35:34.833Z","count":0,"uniques":0},{"timestamp":"2024-05-03T00:38:09.461Z","count":0,"uniques":0},{"timestamp":"2024-05-04T00:35:23.256Z","count":0,"uniques":0}]
