[{"timestamp":"2024-12-04T00:55:07.040Z","count":0,"uniques":0},{"timestamp":"2024-12-05T00:55:02.118Z","count":0,"uniques":0},{"timestamp":"2024-12-06T00:54:30.184Z","count":0,"uniques":0},{"timestamp":"2024-12-07T00:53:27.804Z","count":0,"uniques":0},{"timestamp":"2024-12-08T00:58:49.395Z","count":0,"uniques":0},{"timestamp":"2024-12-09T00:56:42.279Z","count":0,"uniques":0},{"timestamp":"2024-12-10T00:55:53.649Z","count":0,"uniques":0},{"timestamp":"2024-12-11T00:54:38.153Z","count":0,"uniques":0},{"timestamp":"2024-12-12T00:54:32.683Z","count":0,"uniques":0},{"timestamp":"2024-12-13T00:55:20.298Z","count":0,"uniques":0},{"timestamp":"2024-12-14T00:52:16.375Z","count":0,"uniques":0},{"timestamp":"2024-12-15T00:59:03.250Z","count":0,"uniques":0},{"timestamp":"2024-12-16T00:57:09.266Z","count":0,"uniques":0},{"timestamp":"2024-12-17T00:54:39.895Z","count":0,"uniques":0},{"timestamp":"2024-12-18T00:51:55.111Z","count":0,"uniques":0},{"timestamp":"2024-12-19T00:52:38.028Z","count":0,"uniques":0},{"timestamp":"2024-12-20T00:50:07.572Z","count":0,"uniques":0},{"timestamp":"2024-12-21T00:49:13.709Z","count":0,"uniques":0},{"timestamp":"2024-12-22T00:55:14.820Z","count":0,"uniques":0},{"timestamp":"2024-12-23T00:51:05.051Z","count":0,"uniques":0},{"timestamp":"2024-12-24T00:49:30.298Z","count":0,"uniques":0},{"timestamp":"2024-12-25T00:48:53.292Z","count":0,"uniques":0},{"timestamp":"2024-12-26T00:49:27.971Z","count":0,"uniques":0},{"timestamp":"2024-12-27T00:49:41.884Z","count":0,"uniques":0},{"timestamp":"2024-12-28T00:48:55.152Z","count":0,"uniques":0},{"timestamp":"2024-12-29T00:55:30.668Z","count":0,"uniques":0},{"timestamp":"2024-12-30T00:51:26.262Z","count":0,"uniques":0},{"timestamp":"2024-12-31T00:49:41.349Z","count":0,"uniques":0},{"timestamp":"2025-01-01T00:55:32.826Z","count":0,"uniques":0},{"timestamp":"2025-01-02T00:48:53.195Z","count":0,"uniques":0},{"timestamp":"2025-01-03T00:49:16.170Z","count":0,"uniques":0}]
