[{"timestamp":"2024-07-04T00:42:00.392Z","count":0,"uniques":0},{"timestamp":"2024-07-05T06:17:00.264Z","count":0,"uniques":0},{"timestamp":"2024-07-06T00:40:38.330Z","count":0,"uniques":0},{"timestamp":"2024-07-07T00:46:22.889Z","count":0,"uniques":0},{"timestamp":"2024-07-08T00:43:56.424Z","count":0,"uniques":0},{"timestamp":"2024-07-09T00:42:29.395Z","count":0,"uniques":0},{"timestamp":"2024-07-10T00:44:06.554Z","count":0,"uniques":0},{"timestamp":"2024-07-11T00:43:22.091Z","count":0,"uniques":0},{"timestamp":"2024-07-12T00:42:36.392Z","count":0,"uniques":0},{"timestamp":"2024-07-13T00:43:31.615Z","count":0,"uniques":0},{"timestamp":"2024-07-14T00:47:01.511Z","count":0,"uniques":0},{"timestamp":"2024-07-15T00:45:08.219Z","count":0,"uniques":0},{"timestamp":"2024-07-16T00:43:17.644Z","count":0,"uniques":0},{"timestamp":"2024-07-17T00:43:49.220Z","count":0,"uniques":0},{"timestamp":"2024-07-18T00:43:10.037Z","count":0,"uniques":0},{"timestamp":"2024-07-19T00:43:20.778Z","count":0,"uniques":0},{"timestamp":"2024-07-20T00:42:22.556Z","count":0,"uniques":0},{"timestamp":"2024-07-21T00:47:39.951Z","count":0,"uniques":0},{"timestamp":"2024-07-22T00:44:53.417Z","count":0,"uniques":0},{"timestamp":"2024-07-23T00:43:33.740Z","count":0,"uniques":0},{"timestamp":"2024-07-24T00:44:26.017Z","count":0,"uniques":0},{"timestamp":"2024-07-25T00:43:36.933Z","count":0,"uniques":0},{"timestamp":"2024-07-26T00:42:59.590Z","count":0,"uniques":0},{"timestamp":"2024-07-27T00:43:39.443Z","count":0,"uniques":0},{"timestamp":"2024-07-28T00:47:59.048Z","count":0,"uniques":0},{"timestamp":"2024-07-29T00:44:59.528Z","count":0,"uniques":0},{"timestamp":"2024-07-30T00:44:17.632Z","count":0,"uniques":0},{"timestamp":"2024-07-31T00:36:33.083Z","count":0,"uniques":0},{"timestamp":"2024-08-01T00:47:33.358Z","count":0,"uniques":0},{"timestamp":"2024-08-02T00:43:15.091Z","count":0,"uniques":0},{"timestamp":"2024-08-03T00:42:53.417Z","count":0,"uniques":0}]
