[{"timestamp":"2024-05-26T00:44:05.562Z","count":0,"uniques":0},{"timestamp":"2024-05-27T00:42:48.311Z","count":0,"uniques":0},{"timestamp":"2024-05-28T00:41:29.762Z","count":0,"uniques":0},{"timestamp":"2024-05-29T00:43:58.542Z","count":0,"uniques":0},{"timestamp":"2024-05-30T00:41:18.978Z","count":0,"uniques":0},{"timestamp":"2024-05-31T00:40:49.696Z","count":0,"uniques":0},{"timestamp":"2024-06-01T00:44:38.590Z","count":0,"uniques":0},{"timestamp":"2024-06-02T00:45:20.297Z","count":0,"uniques":0}]
