[{"timestamp":"2024-09-09T00:50:21.318Z","count":0,"uniques":0},{"timestamp":"2024-09-10T00:48:50.539Z","count":0,"uniques":0},{"timestamp":"2024-09-11T00:47:31.454Z","count":0,"uniques":0},{"timestamp":"2024-09-12T00:47:43.835Z","count":0,"uniques":0},{"timestamp":"2024-09-13T00:47:07.518Z","count":0,"uniques":0},{"timestamp":"2024-09-14T00:46:55.559Z","count":0,"uniques":0},{"timestamp":"2024-09-15T00:53:28.347Z","count":0,"uniques":0},{"timestamp":"2024-09-16T00:50:13.413Z","count":0,"uniques":0}]
