[{"timestamp":"2024-03-07T00:34:45.714Z","count":0,"uniques":0},{"timestamp":"2024-03-08T00:41:24.558Z","count":0,"uniques":0},{"timestamp":"2024-03-09T00:39:50.728Z","count":0,"uniques":0},{"timestamp":"2024-03-10T00:43:30.210Z","count":0,"uniques":0},{"timestamp":"2024-03-11T00:41:53.456Z","count":0,"uniques":0},{"timestamp":"2024-03-12T00:40:58.316Z","count":0,"uniques":0},{"timestamp":"2024-03-13T00:41:47.510Z","count":0,"uniques":0},{"timestamp":"2024-03-14T00:41:01.814Z","count":0,"uniques":0}]
