[{"timestamp":"2024-12-11T00:58:05.902Z","count":0,"uniques":0},{"timestamp":"2024-12-12T00:57:59.625Z","count":0,"uniques":0},{"timestamp":"2024-12-13T00:58:45.549Z","count":0,"uniques":0},{"timestamp":"2024-12-14T00:55:41.214Z","count":0,"uniques":0},{"timestamp":"2024-12-15T01:02:35.277Z","count":0,"uniques":0},{"timestamp":"2024-12-16T01:00:39.401Z","count":0,"uniques":0},{"timestamp":"2024-12-17T00:58:06.634Z","count":0,"uniques":0},{"timestamp":"2024-12-18T00:55:29.191Z","count":0,"uniques":0}]
