[{"timestamp":"2024-02-22T00:41:09.879Z","count":0,"uniques":0},{"timestamp":"2024-02-23T00:40:36.970Z","count":0,"uniques":0},{"timestamp":"2024-02-24T00:38:37.497Z","count":0,"uniques":0},{"timestamp":"2024-02-25T00:44:49.620Z","count":0,"uniques":0},{"timestamp":"2024-02-26T00:42:25.153Z","count":0,"uniques":0},{"timestamp":"2024-02-27T00:40:56.510Z","count":0,"uniques":0},{"timestamp":"2024-02-28T00:40:39.132Z","count":0,"uniques":0},{"timestamp":"2024-02-29T00:40:27.210Z","count":0,"uniques":0}]
