[{"timestamp":"2024-10-02T00:53:08.075Z","count":0,"uniques":0},{"timestamp":"2024-10-03T00:53:00.736Z","count":0,"uniques":0},{"timestamp":"2024-10-04T00:52:22.685Z","count":0,"uniques":0},{"timestamp":"2024-10-05T00:52:47.776Z","count":0,"uniques":0},{"timestamp":"2024-10-06T00:56:30.439Z","count":0,"uniques":0},{"timestamp":"2024-10-07T00:53:52.252Z","count":0,"uniques":0},{"timestamp":"2024-10-08T00:52:50.975Z","count":0,"uniques":0},{"timestamp":"2024-10-09T00:52:44.113Z","count":0,"uniques":0}]
