[{"timestamp":"2024-12-21T00:52:54.090Z","count":0,"uniques":0},{"timestamp":"2024-12-22T00:59:01.238Z","count":0,"uniques":0},{"timestamp":"2024-12-23T00:54:30.097Z","count":0,"uniques":0},{"timestamp":"2024-12-24T00:52:59.031Z","count":0,"uniques":0},{"timestamp":"2024-12-25T00:52:25.563Z","count":0,"uniques":0},{"timestamp":"2024-12-26T00:53:13.641Z","count":0,"uniques":0},{"timestamp":"2024-12-27T00:53:27.751Z","count":0,"uniques":0},{"timestamp":"2024-12-28T00:52:44.363Z","count":0,"uniques":0}]
