[{"timestamp":"2024-04-28T00:47:44.782Z","count":0,"uniques":0},{"timestamp":"2024-04-29T00:43:23.368Z","count":0,"uniques":0},{"timestamp":"2024-04-30T00:41:04.331Z","count":0,"uniques":0},{"timestamp":"2024-05-01T00:44:59.319Z","count":0,"uniques":0},{"timestamp":"2024-05-02T00:42:30.647Z","count":0,"uniques":0},{"timestamp":"2024-05-03T00:44:48.986Z","count":0,"uniques":0},{"timestamp":"2024-05-04T00:42:24.687Z","count":0,"uniques":0},{"timestamp":"2024-05-05T00:45:21.029Z","count":0,"uniques":0}]
