[{"timestamp":"2024-01-11T00:37:41.309Z","count":0,"uniques":0},{"timestamp":"2024-01-12T00:37:53.517Z","count":0,"uniques":0},{"timestamp":"2024-01-13T00:37:30.721Z","count":0,"uniques":0},{"timestamp":"2024-01-14T00:40:39.365Z","count":0,"uniques":0},{"timestamp":"2024-01-15T00:39:12.330Z","count":0,"uniques":0},{"timestamp":"2024-01-16T00:37:33.833Z","count":0,"uniques":0},{"timestamp":"2024-01-17T00:37:44.994Z","count":0,"uniques":0},{"timestamp":"2024-01-18T00:37:25.809Z","count":0,"uniques":0}]
