[{"timestamp":"2023-11-21T00:42:08.921Z","count":0,"uniques":0},{"timestamp":"2023-11-22T00:42:42.238Z","count":0,"uniques":0},{"timestamp":"2023-11-23T00:40:35.538Z","count":0,"uniques":0},{"timestamp":"2023-11-24T00:39:45.560Z","count":0,"uniques":0},{"timestamp":"2023-11-25T00:39:12.676Z","count":0,"uniques":0},{"timestamp":"2023-11-26T00:43:55.704Z","count":0,"uniques":0},{"timestamp":"2023-11-27T00:41:25.135Z","count":0,"uniques":0},{"timestamp":"2023-11-28T00:41:34.064Z","count":0,"uniques":0}]
