[{"timestamp":"2024-10-03T00:52:37.466Z","count":0,"uniques":0},{"timestamp":"2024-10-04T00:52:01.668Z","count":0,"uniques":0},{"timestamp":"2024-10-05T00:52:23.692Z","count":0,"uniques":0},{"timestamp":"2024-10-06T00:56:09.734Z","count":0,"uniques":0},{"timestamp":"2024-10-07T00:53:31.472Z","count":0,"uniques":0},{"timestamp":"2024-10-08T00:52:27.782Z","count":0,"uniques":0},{"timestamp":"2024-10-09T00:52:21.142Z","count":0,"uniques":0},{"timestamp":"2024-10-10T00:51:56.394Z","count":0,"uniques":0}]
